airflow_postmark/__init__.py
airflow_postmark/postmark.py
airflow_postmark-0.0.3.dist-info/METADATA
airflow_postmark-0.0.3.dist-info/WHEEL
airflow_postmark-0.0.3.dist-info/top_level.txt
airflow_postmark-0.0.3.dist-info/RECORD
