Metadata-Version: 2.1
Name: airflow-postmark
Version: 0.0.3
Summary: airflow postmark support
Home-page: UNKNOWN
Author: UNKNOWN
Author-email: songpa@gmail.com
License: MIT
Platform: UNKNOWN
Classifier: Development Status :: 4 - Beta
Classifier: Programming Language :: Python :: 3.6
Requires-Dist: pystmark
